mrz/__init__.py
mrz/base/countries.py
mrz/base/countries_ops.py
mrz/base/errors.py
mrz/base/functions.py
mrz/base/string_checkers.py
mrz/checker/__init__.py
mrz/checker/_enums.py
mrz/checker/_fields.py
mrz/checker/_hash_fields.py
mrz/checker/_honorifics.py
mrz/checker/_report.py
mrz/checker/mrva.py
mrz/checker/mrvb.py
mrz/checker/td1.py
mrz/checker/td2.py
mrz/checker/td3.py
mrz/checker/test1.py
mrz/checker/test2.py
mrz/generator/__init__.py
mrz/generator/_fields.py
mrz/generator/_hash_fields.py
mrz/generator/_holder_name.py
mrz/generator/_transliterations.py
mrz/generator/mrva.py
mrz/generator/mrvb.py
mrz/generator/td1.py
mrz/generator/td2.py
mrz/generator/td3.py
mrz/generator/dictionaries/__init__.py
mrz/generator/dictionaries/arabic.py
mrz/generator/dictionaries/cyrillic.py
mrz/generator/dictionaries/cyrillic_belarussian.py
mrz/generator/dictionaries/cyrillic_bulgarian.py
mrz/generator/dictionaries/cyrillic_macedonian.py
mrz/generator/dictionaries/cyrillic_serbian.py
mrz/generator/dictionaries/cyrillic_ukrainian.py
mrz/generator/dictionaries/greek.py
mrz/generator/dictionaries/hebrew.py
mrz/generator/dictionaries/latin_based.py
mrz-0.6.2.dist-info/LICENSE
mrz-0.6.2.dist-info/METADATA
mrz-0.6.2.dist-info/WHEEL
mrz-0.6.2.dist-info/top_level.txt
mrz-0.6.2.dist-info/RECORD
