Metadata-Version: 1.1
Name: mrz
Version: 0.6.2
Summary: Machine readable zone generator and checker for passports, visas, id cards and other travel documents
Home-page: https://github.com/Arg0s1080/mrz
Author: Ivan Rincon
Author-email: ivan.rincon76@gmail.com
License: GPLv3
Keywords: mrz passports visas id cards td1 td2 td3 mrva mrvb icao
Platform: UNKNOWN
Classifier: Development Status :: 4 - Beta
Classifier: License :: OSI Approved :: GNU General Public License v3 (GPLv3)
Classifier: Programming Language :: Python :: 3
Classifier: Programming Language :: Python :: 3.4
Classifier: Programming Language :: Python :: 3.5
Classifier: Programming Language :: Python :: 3.6
Classifier: Programming Language :: Python :: 3.7
Classifier: Programming Language :: Python :: 3.8
Classifier: Topic :: Security
